ccpp/__init__.py
ccpp/ccpp-tmpl/cookiecutter.json
ccpp/ccpp-tmpl/{{ cookiecutter.repo }}/.gitignore
ccpp/ccpp-tmpl/{{ cookiecutter.repo }}/CHANGELOG.md
ccpp/ccpp-tmpl/{{ cookiecutter.repo }}/LICENSE
ccpp/ccpp-tmpl/{{ cookiecutter.repo }}/pyproject.toml
ccpp/ccpp-tmpl/{{ cookiecutter.repo }}/README.md
ccpp/ccpp-tmpl/{{ cookiecutter.repo }}/tests/__init__.py
ccpp/ccpp-tmpl/{{ cookiecutter.repo }}/tests/test_{{ cookiecutter.repo_src }}.py
ccpp/ccpp-tmpl/{{ cookiecutter.repo }}/{{ cookiecutter.repo_src }}/__init__.py
ccpp/ccpp-tmpl/{{ cookiecutter.repo }}/{{ cookiecutter.repo_src }}/main.py
ccpp/generate.py
ccpp/main.py
ccpp-0.1.4.dist-info/entry_points.txt
ccpp-0.1.4.dist-info/LICENSE
ccpp-0.1.4.dist-info/WHEEL
ccpp-0.1.4.dist-info/METADATA
ccpp-0.1.4.dist-info/RECORD
