Metadata-Version: 2.1
Name: ccpp
Version: 0.1.4
Summary: Cookiecutter template for Python package
Home-page: https://github.com/guaifish/ccpp
License: MIT
Author: guaifish
Author-email: guaifish@hotmail.com
Requires-Python: >=3.6,<4.0
Classifier: License :: OSI Approved :: MIT License
Classifier: Programming Language :: Python :: 3
Classifier: Programming Language :: Python :: 3.6
Classifier: Programming Language :: Python :: 3.7
Classifier: Programming Language :: Python :: 3.8
Requires-Dist: cookiecutter (>=1.7.2,<2.0.0)
Requires-Dist: fire (>=0.3.1,<0.4.0)
Requires-Dist: poetry (>=1.0.9,<2.0.0)
Project-URL: Repository, https://github.com/guaifish/ccpp
